alibabacloud_safconsole20250521/__init__.py
alibabacloud_safconsole20250521/client.py
alibabacloud_safconsole20250521/models/__init__.py
alibabacloud_safconsole20250521/models/_create_customer_module_basic_info_request.py
alibabacloud_safconsole20250521/models/_create_customer_module_basic_info_response.py
alibabacloud_safconsole20250521/models/_create_customer_module_basic_info_response_body.py
alibabacloud_safconsole20250521/models/_create_customer_module_meta_info_request.py
alibabacloud_safconsole20250521/models/_create_customer_module_meta_info_response.py
alibabacloud_safconsole20250521/models/_create_customer_module_meta_info_response_body.py
alibabacloud_safconsole20250521/models/_create_customer_module_output_info_request.py
alibabacloud_safconsole20250521/models/_create_customer_module_output_info_response.py
alibabacloud_safconsole20250521/models/_create_customer_module_output_info_response_body.py
alibabacloud_safconsole20250521/models/_delete_model_request.py
alibabacloud_safconsole20250521/models/_delete_model_response.py
alibabacloud_safconsole20250521/models/_delete_model_response_body.py
alibabacloud_safconsole20250521/models/_describe_customer_module_basic_info_request.py
alibabacloud_safconsole20250521/models/_describe_customer_module_basic_info_response.py
alibabacloud_safconsole20250521/models/_describe_customer_module_basic_info_response_body.py
alibabacloud_safconsole20250521/models/_describe_customer_module_meta_info_request.py
alibabacloud_safconsole20250521/models/_describe_customer_module_meta_info_response.py
alibabacloud_safconsole20250521/models/_describe_customer_module_meta_info_response_body.py
alibabacloud_safconsole20250521/models/_describe_customer_module_output_info_request.py
alibabacloud_safconsole20250521/models/_describe_customer_module_output_info_response.py
alibabacloud_safconsole20250521/models/_describe_customer_module_output_info_response_body.py
alibabacloud_safconsole20250521-1.1.0.dist-info/LICENSE
alibabacloud_safconsole20250521-1.1.0.dist-info/METADATA
alibabacloud_safconsole20250521-1.1.0.dist-info/WHEEL
alibabacloud_safconsole20250521-1.1.0.dist-info/top_level.txt
alibabacloud_safconsole20250521-1.1.0.dist-info/RECORD
